{
  "image": [
    ".bmp",
    ".cr2",
    ".gif",
    ".ico",
    ".ithmb",
    ".jpeg",
    ".jpg",
    ".nef",
    ".png",
    ".raw",
    ".svg",
    ".tif",
    ".tiff",
    ".wbmp",
    ".webp"
  ],
  "audio": [
    ".aac",
    ".aif",
    ".aifc",
    ".aiff",
    ".au",
    ".flac",
    ".m4a",
    ".mid",
    ".mp3",
    ".m4b",
    ".m4p",
    ".m4r",
    ".oga",
    ".ogg",
    ".opus",
    ".ra",
    ".ram",
    ".spx",
    ".wav",
    ".wm"
  ],
  "video": [
    ".3gp",
    ".3gpp",
    ".3gpp2",
    ".3g2",
    ".asf",
    ".avi",
    ".dv",
    ".dvi",
    ".flv",
    ".m2t",
    ".mp4",
    ".m4v",
    ".mkv",
    ".mov",
    ".mpeg",
    ".mpg",
    ".mts",
    ".ogv",
    ".ogx",
    ".rm",
    ".rmvb",
    ".ts",
    ".vob",
    ".webm",
    ".wmv"
  ],
  "document": [
    ".csv",
    ".doc",
    ".dochtml",
    ".docm",
    ".docx",
    ".docxml",
    ".dot",
    ".dothtml",
    ".dotm",
    ".dotx",
    ".eps",
    ".fdf",
    ".key",
    ".keynote",
    ".kth",
    ".mpp",
    ".mpt",
    ".mpx",
    ".mpd",
    ".nmbtemplate",
    ".numbers",
    ".odc",
    ".odp",
    ".odg",
    ".ods",
    ".odt",
    ".pages",
    ".pdf",
    ".pdfxml",
    ".pot",
    ".pothtml",
    ".potm",
    ".potx",
    ".ppa",
    ".ppam",
    ".pps",
    ".ppsm",
    ".ppsx",
    ".ppt",
    ".ppthtml",
    ".pptm",
    ".pptx",
    ".pptxml",
    ".prn",
    ".ps",
    ".pwz",
    ".rtf",
    ".tab",
    ".template",
    ".tsv",
    ".txt",
    ".vdx",
    ".vsd",
    ".vss",
    ".vst",
    ".vsx",
    ".vtx",
    ".wpd",
    ".wps",
    ".xdp",
    ".xdf",
    ".xlam",
    ".xll",
    ".xlr",
    ".xls",
    ".xlsb",
    ".xlsm",
    ".xlsx",
    ".xltm",
    ".xltx",
    ".xps",
    ".wbk",
    ".wpd",
    ".wpl"
  ],
  "text": [
    ".applescript",
    ".as",
    ".as3",
    ".c",
    ".cc",
    ".clisp",
    ".coffee",
    ".cpp",
    ".cs",
    ".css",
    ".csv",
    ".cxx",
    ".def",
    ".diff",
    ".erl",
    ".fountain",
    ".ft",
    ".h",
    ".hpp",
    ".htm",
    ".html",
    ".hxx",
    ".inc",
    ".ini",
    ".java",
    ".js",
    ".json",
    ".less",
    ".log",
    ".lua",
    ".m",
    ".mm",
    ".markdown",
    ".mat",
    ".md",
    ".mdown",
    ".mkdn",
    ".mustache",
    ".mxml",
    ".patch",
    ".php",
    ".phtml",
    ".pl",
    ".plist",
    ".properties",
    ".py",
    ".rb",
    ".sass",
    ".scss",
    ".sh",
    ".shtml",
    ".sql",
    ".tab",
    ".taskpaper",
    ".tex",
    ".text",
    ".tmpl",
    ".tsv",
    ".txt",
    ".url",
    ".vb",
    ".xhtml",
    ".xml",
    ".yaml",
    ".yml"
  ]
}
